easysurrogate/__init__.py
easysurrogate/campaign.py
easysurrogate/analysis/ANN_analysis.py
easysurrogate/analysis/CCM_analysis.py
easysurrogate/analysis/DAS_analysis.py
easysurrogate/analysis/GP_analysis.py
easysurrogate/analysis/KMN_analysis.py
easysurrogate/analysis/QSN_analysis.py
easysurrogate/analysis/__init__.py
easysurrogate/analysis/base.py
easysurrogate/methods/Concatenate.py
easysurrogate/methods/CumSum_Layer.py
easysurrogate/methods/DAS_Layer.py
easysurrogate/methods/DAS_network.py
easysurrogate/methods/Feature_Engineering.py
easysurrogate/methods/GP.py
easysurrogate/methods/Layer.py
easysurrogate/methods/NN.py
easysurrogate/methods/Neuron.py
easysurrogate/methods/Post_Processing.py
easysurrogate/methods/SimpleBin.py
easysurrogate/methods/__init__.py
easysurrogate/methods/ann_surrogate.py
easysurrogate/methods/batch_normalization.py
easysurrogate/methods/ccm_surrogate.py
easysurrogate/methods/das_surrogate.py
easysurrogate/methods/gaussian_process_regressor.py
easysurrogate/methods/gp_surrogate.py
easysurrogate/methods/kmn_surrogate.py
easysurrogate/methods/qsn_surrogate.py
easysurrogate/methods/reduced_surrogate.py
easysurrogate/methods/resampling.py
easysurrogate-0.24.2.dist-info/LICENSE
easysurrogate-0.24.2.dist-info/METADATA
easysurrogate-0.24.2.dist-info/WHEEL
easysurrogate-0.24.2.dist-info/top_level.txt
easysurrogate-0.24.2.dist-info/RECORD
